setup.cfg
setup.py
xivo_test_helpers/__init__.py
xivo_test_helpers/asset_launching_test_case.py
xivo_test_helpers/until.py
xivo_test_helpers.egg-info/PKG-INFO
xivo_test_helpers.egg-info/SOURCES.txt
xivo_test_helpers.egg-info/dependency_links.txt
xivo_test_helpers.egg-info/requires.txt
xivo_test_helpers.egg-info/top_level.txt