Metadata-Version: 1.1
Name: xivo-test-helpers
Version: 0.1.5
Summary: XiVO test helpers
Home-page: https://github.com/xivo-pbx/xivo-test-helpers
Author: Avencall
Author-email: dev@avencall.com
License: UNKNOWN
Download-URL: https://github.com/xivo-pbx/xivo-test-helpers/tarball/0.1.5
Platform: UNKNOWN
